[
  {
    "name": "植物大战僵尸杂交版v3.15",
    "version": "3.15",
    "build": "PvZ-HE v3.15",
    "release_date": "2026-01-22",
    "download_url": "https://pan.mcbebbs.cn/f/Ja7fN/pvzzjv3.15.zip"
  },
  {
    "name": "植物大战僵尸融合版v3.3.1",
    "version": "3.3.1",
    "build": "PVZRH-v3.3.1",
    "release_date": "2026-01-21",
    "download_url": "https://pan.mcbebbs.cn/f/vlVhQ/pvzrhv3.1.1.zip"
  },
  {
    "name": "植物大战僵尸杂交重制版v0.14",
    "version": "0.14",
    "build": "PVZ-HE v0.14",
    "release_date": "2026-1-31",
    "download_url": "https://pan.mcbebbs.cn/f/VYVcN/pvzzjfv0.14.zip"
  }
]